{"name":null,"assets":"aoy4:pathy15:img%2Fblack.pngy4:sizei24425y4:typey5:IMAGEy2:idR1goR0y31:img%2Fbuttons%2FBack_Button.pngR2i20412R3R4R5R6goR0y33:img%2Fbuttons%2FCredit_Button.pngR2i20132R3R4R5R7goR0y38:img%2Fbuttons%2FLeaderboard_Button.pngR2i21198R3R4R5R8goR0y32:img%2Fbuttons%2FMusic_Button.pngR2i21721R3R4R5R9goR0y31:img%2Fbuttons%2Fokay_Button.pngR2i20640R3R4R5R10goR0y31:img%2Fbuttons%2FPlay_Button.pngR2i21508R3R4R5R11goR0y31:img%2Fbuttons%2FQuit_Button.pngR2i20052R3R4R5R12goR0y32:img%2Fbuttons%2FStart_Button.pngR2i20477R3R4R5R13goR0y15:img%2Fwhite.pngR2i46349R3R4R5R14goR0y16:img%2Fwhiter.pngR2i25762R3R4R5R15goR0y17:data%2Fcredits.dbR2i2048R3y6:BINARYR5R16goR0y20:data%2Fhighscores.dbR2i3072R3R17R5R18goR0y12:data%2FQ1.dbR2i3072R3R17R5R19goR0y15:music%2FOUT.wavR2i326686R3y5:SOUNDR5R20goR0y15:music%2FSFX.wavR2i326686R3R21R5R22goR0y20:music%2Fwhiteguy.wavR2i40045046R3R21R5R23goR2i163476R3y4:FONTy9:classNamey26:__ASSET__fonts_papyrus_ttfR5y19:fonts%2FPAPYRUS.TTFgh","version":2,"libraryArgs":[],"libraryType":null}